xmcp_server_wxauto/__init__.py
xmcp_server_wxauto/__main__.py
xmcp_server_wxauto/server.py
xmcp_server_wxauto-0.1.4.dist-info/METADATA
xmcp_server_wxauto-0.1.4.dist-info/WHEEL
xmcp_server_wxauto-0.1.4.dist-info/entry_points.txt
xmcp_server_wxauto-0.1.4.dist-info/RECORD
