Metadata-Version: 2.4
Name: xmcp-server-wxauto
Version: 0.1.4
Summary: 自动操作微信MCP服务
Requires-Python: >=3.10
Requires-Dist: mcp[cli]>=1.9.4
Requires-Dist: wxauto>=39.1.4
